Metadata-Version: 1.1
Name: secure-socket
Version: 1.0.1
Summary: a secured socket
Home-page: UNKNOWN
Author: YOUR NAME
Author-email: your.email@domain.com
License: MIT
Keywords: secure,asymmetric,encoding,socket
Platform: UNKNOWN
Classifier: Development Status :: 3 - Alpha
Classifier: Intended Audience :: Developers
Classifier: Topic :: Software Development :: Build Tools
Classifier: License :: OSI Approved :: MIT License
Classifier: Programming Language :: Python :: 3
Classifier: Programming Language :: Python :: 3.4
Classifier: Programming Language :: Python :: 3.5
Classifier: Programming Language :: Python :: 3.6
Classifier: Programming Language :: Python :: 3.7
Classifier: Programming Language :: Python :: 3.8
